awsgi/__init__.py
aws_wsgi-0.2.6.dist-info/LICENSE.txt
aws_wsgi-0.2.6.dist-info/METADATA
aws_wsgi-0.2.6.dist-info/WHEEL
aws_wsgi-0.2.6.dist-info/top_level.txt
aws_wsgi-0.2.6.dist-info/RECORD
