Metadata-Version: 2.1
Name: aws-wsgi
Version: 0.2.6
Summary: WSGI adapter for AWS API Gateway/Lambda Proxy Integration
Home-page: https://github.com/slank/awsgi
Author: Matthew Wedgwood
Author-email: github+awsgi@smacky.org
License: MIT
Keywords: wsgi aws lambda api gateway
Platform: UNKNOWN
Classifier: Development Status :: 3 - Alpha
Classifier: Intended Audience :: Developers
Classifier: Topic :: Internet :: WWW/HTTP :: HTTP Servers
Classifier: License :: OSI Approved :: MIT License
Classifier: Programming Language :: Python :: 2
Classifier: Programming Language :: Python :: 2.7
Classifier: Programming Language :: Python :: 3
Classifier: Programming Language :: Python :: 3.3
Classifier: Programming Language :: Python :: 3.4
Classifier: Programming Language :: Python :: 3.5
